mesh4d/__init__.py
mesh4d/field.py
mesh4d/kps.py
mesh4d/obj3d.py
mesh4d/obj4d.py
mesh4d/utils.py
mesh4d-0.4.dist-info/licenses/LICENSE.md
mesh4d-0.4.dist-info/METADATA
mesh4d-0.4.dist-info/WHEEL
mesh4d-0.4.dist-info/top_level.txt
mesh4d-0.4.dist-info/RECORD
