Metadata-Version: 2.4
Name: mesh4d
Version: 0.4
Summary: Toolkit for 4D (3D + T) data visualisation, operation, and dynamic dense-registration. Extents the existing concepts of 3D mesh toolkit to a 4D mesh toolkit.
Author-email: Qilong Liu <qilong-kirov.liu@outlook.com>
License: MIT
Project-URL: Repository, https://github.com/liu-qilong/mesh4d
Requires-Python: >=3.7
License-File: LICENSE.md
Requires-Dist: open3d
Requires-Dist: pyvista[all]
Requires-Dist: probreg
Requires-Dist: numpy
Requires-Dist: pandas
Requires-Dist: scipy
Requires-Dist: matplotlib
Dynamic: license-file
